iglu_python/__init__.py
iglu_python/above_percent.py
iglu_python/active_percent.py
iglu_python/adrr.py
iglu_python/auc.py
iglu_python/below_percent.py
iglu_python/cogi.py
iglu_python/conga.py
iglu_python/cv_glu.py
iglu_python/cv_measures.py
iglu_python/ea1c.py
iglu_python/episode_calculation.py
iglu_python/gmi.py
iglu_python/grade.py
iglu_python/grade_eugly.py
iglu_python/grade_hyper.py
iglu_python/grade_hypo.py
iglu_python/gri.py
iglu_python/gvp.py
iglu_python/hbgi.py
iglu_python/hyper_index.py
iglu_python/hypo_index.py
iglu_python/igc.py
iglu_python/in_range_percent.py
iglu_python/iqr_glu.py
iglu_python/j_index.py
iglu_python/lbgi.py
iglu_python/m_value.py
iglu_python/mad_glu.py
iglu_python/mag.py
iglu_python/mage.py
iglu_python/mean_glu.py
iglu_python/median_glu.py
iglu_python/modd.py
iglu_python/pgs.py
iglu_python/process_data.py
iglu_python/quantile_glu.py
iglu_python/range_glu.py
iglu_python/roc.py
iglu_python/sd_glu.py
iglu_python/sd_measures.py
iglu_python/sd_roc.py
iglu_python/summary_glu.py
iglu_python/utils.py
iglu_python/extension/load_data.py
iglu_python/extension/plots.py
iglu_python-0.4.1.dist-info/METADATA
iglu_python-0.4.1.dist-info/WHEEL
iglu_python-0.4.1.dist-info/licenses/LICENSE
iglu_python-0.4.1.dist-info/RECORD
