Metadata-Version: 2.4
Name: iglu_python
Version: 0.4.1
Summary: Python implementation of the iglu package for continuous glucose monitoring data analysis
Project-URL: Homepage, https://github.com/staskh/iglu_python
Project-URL: Documentation, https://iglu-python.readthedocs.io/
Project-URL: Repository, https://github.com/staskh/iglu_python.git
Project-URL: Issues, https://github.com/staskh/iglu_python/issues
Author-email: Stas Khirmanv <stas@khirman.com>
License: GPL2
License-File: LICENSE
Classifier: Development Status :: 4 - Beta
Classifier: Intended Audience :: Science/Research
Classifier: License :: OSI Approved :: MIT License
Classifier: Programming Language :: Python :: 3
Classifier: Programming Language :: Python :: 3.8
Classifier: Programming Language :: Python :: 3.9
Classifier: Programming Language :: Python :: 3.10
Classifier: Programming Language :: Python :: 3.11
Classifier: Topic :: Scientific/Engineering :: Medical Science Apps.
Requires-Python: >=3.11
Requires-Dist: matplotlib
Requires-Dist: numpy
Requires-Dist: openpyxl
Requires-Dist: pandas
Requires-Dist: pyarrow>=21.0.0
Requires-Dist: tzlocal
Provides-Extra: build
Requires-Dist: hatch>=1.14.1; extra == 'build'
Requires-Dist: twine>=6.2.0; extra == 'build'
Provides-Extra: dev
Requires-Dist: black>=25.1.0; extra == 'dev'
Requires-Dist: hatch>=1.14.1; extra == 'dev'
Requires-Dist: isort>=5.0.0; extra == 'dev'
Requires-Dist: mypy>=1.0.0; extra == 'dev'
Requires-Dist: pre-commit>=3.0.0; extra == 'dev'
Requires-Dist: pyarrow>=21.0.0; extra == 'dev'
Requires-Dist: pytest-cov>=7.0.0; extra == 'dev'
Requires-Dist: pytest>=8.4.2; extra == 'dev'
Requires-Dist: ruff>=0.1.0; extra == 'dev'
Requires-Dist: twine>=6.2.0; extra == 'dev'
Provides-Extra: lint
Requires-Dist: black>=25.1.0; extra == 'lint'
Requires-Dist: isort>=5.0.0; extra == 'lint'
Requires-Dist: mypy>=1.0.0; extra == 'lint'
Requires-Dist: pre-commit>=3.0.0; extra == 'lint'
Requires-Dist: ruff>=0.1.0; extra == 'lint'
Provides-Extra: test
Requires-Dist: pytest-cov>=7.0.0; extra == 'test'
Requires-Dist: pytest>=8.4.2; extra == 'test'
